pyconfigurableml/__init__.py
pyconfigurableml/_core.py
pyconfigurableml/azure.py
pyconfigurableml/entry.py
pyconfigurableml/files.py
pyconfigurableml/logging.py
pyconfigurableml/munch.py
pyconfigurableml-0.5.0.dist-info/LICENSE
pyconfigurableml-0.5.0.dist-info/METADATA
pyconfigurableml-0.5.0.dist-info/WHEEL
pyconfigurableml-0.5.0.dist-info/top_level.txt
pyconfigurableml-0.5.0.dist-info/RECORD
