Metadata-Version: 2.1
Name: pyconfigurableml
Version: 0.5.0
Summary: Configurable ML in Python
Home-page: https://github.com/dkmiller/pyconfigurableml
Author: Daniel Miller
Author-email: daniel.keegan.miller@gmail.com
License: MIT
Platform: UNKNOWN
Classifier: License :: OSI Approved :: MIT License
Classifier: Programming Language :: Python :: 3
Classifier: Programming Language :: Python :: 3.6
Classifier: Programming Language :: Python :: 3.7
Classifier: Programming Language :: Python :: 3.8
Requires-Python: ~=3.6
Requires-Dist: typeguard (>=2.9.1)
Requires-Dist: pyyaml (>=5.3.1)
Requires-Dist: requests (>=2.24.0)
Provides-Extra: azure
Requires-Dist: azure-identity (>=1.3.1) ; extra == 'azure'
Requires-Dist: azure-keyvault-secrets (>=4.1.0) ; extra == 'azure'
Provides-Extra: munch
Requires-Dist: munch (>=2.5.0) ; extra == 'munch'
